setup.py
i3situation/__init__.py
i3situation/main.py
i3situation.egg-info/PKG-INFO
i3situation.egg-info/SOURCES.txt
i3situation.egg-info/dependency_links.txt
i3situation.egg-info/entry_points.txt
i3situation.egg-info/requires.txt
i3situation.egg-info/top_level.txt
i3situation/core/__init__.py
i3situation/core/config.py
i3situation/core/plugin_manager.py
i3situation/core/status.py
i3situation/plugins/__init__.py
i3situation/plugins/_plugin.py
i3situation/plugins/battery.py
i3situation/plugins/cmus.py
i3situation/plugins/conky.py
i3situation/plugins/date_time.py
i3situation/plugins/reddit.py
i3situation/plugins/run.py
i3situation/plugins/text.py