Metadata-Version: 1.0
Name: i3situation
Version: 1.0.3
Summary: A replacement for i3status that allows for the use of plugins.
Home-page: https://github.com/HarveyHunt/i3situation
Author: Harvey Hunt
Author-email: harveyhuntnexus@gmail.com
License: GPLv3
Keywords: python3 i3situation i3 i3wm i3status i3bar json
Platform: UNKNOWN
